_droute_core.cpython-311-darwin.so
libdmc_route.0.5.1.dylib
libdmc_route.0.dylib
libdmc_route.dylib
pydmc_route.py
droute/__init__.py
droute/_version.py
droute-0.5.1.dist-info/licenses/LICENSE
droute-0.5.1.dist-info/METADATA
droute-0.5.1.dist-info/WHEEL
droute-0.5.1.dist-info/top_level.txt
droute-0.5.1.dist-info/RECORD
