Metadata-Version: 2.4
Name: droute
Version: 0.5.1
Summary: Differentiable river routing library for hydrological modeling
Author-email: Darri Eythorsson <darri.eythorsson@ucalgary.ca>
License: MIT License
Project-URL: Homepage, https://github.com/DarriEy/dRoute
Project-URL: Documentation, https://github.com/DarriEy/dRoute#readme
Project-URL: Repository, https://github.com/DarriEy/dRoute
Project-URL: Bug Tracker, https://github.com/DarriEy/dRoute/issues
Project-URL: Source Code, https://github.com/DarriEy/dRoute
Keywords: hydrology,routing,muskingum-cunge,differentiable,machine-learning
Classifier: Development Status :: 4 - Beta
Classifier: Intended Audience :: Science/Research
Classifier: License :: OSI Approved :: MIT License
Classifier: Programming Language :: Python :: 3
Classifier: Programming Language :: Python :: 3.8
Classifier: Programming Language :: Python :: 3.9
Classifier: Programming Language :: Python :: 3.10
Classifier: Programming Language :: Python :: 3.11
Classifier: Programming Language :: Python :: 3.12
Classifier: Programming Language :: Python :: 3.13
Classifier: Programming Language :: C++
Classifier: Operating System :: OS Independent
Classifier: Topic :: Scientific/Engineering
Classifier: Topic :: Scientific/Engineering :: Hydrology
Requires-Python: >=3.8
License-File: LICENSE
Requires-Dist: numpy>=1.20.0
Provides-Extra: torch
Requires-Dist: torch>=1.9.0; extra == "torch"
Provides-Extra: dev
Requires-Dist: pytest>=6.0; extra == "dev"
Requires-Dist: pytest-cov; extra == "dev"
Requires-Dist: black; extra == "dev"
Requires-Dist: flake8; extra == "dev"
Dynamic: license-file
